aerosoltools/__init__.py
aerosoltools/aerosol1d.py
aerosoltools/aerosol2d.py
aerosoltools/aerosolalt.py
aerosoltools/__pycache__/__init__.cpython-312.pyc
aerosoltools/__pycache__/__init__.cpython-39.pyc
aerosoltools/__pycache__/aerosol1d.cpython-312.pyc
aerosoltools/__pycache__/aerosol1d.cpython-39.pyc
aerosoltools/__pycache__/aerosol2d.cpython-312.pyc
aerosoltools/__pycache__/aerosol2d.cpython-39.pyc
aerosoltools/__pycache__/aerosolalt.cpython-312.pyc
aerosoltools/__pycache__/aerosolalt.cpython-39.pyc
aerosoltools/loaders/Aethalometer.py
aerosoltools/loaders/CPC.py
aerosoltools/loaders/Common.py
aerosoltools/loaders/Discmini.py
aerosoltools/loaders/ELPI.py
aerosoltools/loaders/FMPS.py
aerosoltools/loaders/Fourtec.py
aerosoltools/loaders/Grimm.py
aerosoltools/loaders/NS.py
aerosoltools/loaders/OPCN3.py
aerosoltools/loaders/OPS.py
aerosoltools/loaders/Partector.py
aerosoltools/loaders/SMPS.py
aerosoltools/loaders/__init__.py
aerosoltools/loaders/__pycache__/Aethalometer.cpython-312.pyc
aerosoltools/loaders/__pycache__/Aethalometer.cpython-39.pyc
aerosoltools/loaders/__pycache__/CPC.cpython-312.pyc
aerosoltools/loaders/__pycache__/CPC.cpython-39.pyc
aerosoltools/loaders/__pycache__/Common.cpython-312.pyc
aerosoltools/loaders/__pycache__/Common.cpython-39.pyc
aerosoltools/loaders/__pycache__/Discmini.cpython-312.pyc
aerosoltools/loaders/__pycache__/Discmini.cpython-39.pyc
aerosoltools/loaders/__pycache__/ELPI.cpython-312.pyc
aerosoltools/loaders/__pycache__/ELPI.cpython-39.pyc
aerosoltools/loaders/__pycache__/FMPS.cpython-312.pyc
aerosoltools/loaders/__pycache__/FMPS.cpython-39.pyc
aerosoltools/loaders/__pycache__/Fourtec.cpython-312.pyc
aerosoltools/loaders/__pycache__/Fourtec.cpython-39.pyc
aerosoltools/loaders/__pycache__/Grimm.cpython-312.pyc
aerosoltools/loaders/__pycache__/Grimm.cpython-39.pyc
aerosoltools/loaders/__pycache__/NS.cpython-312.pyc
aerosoltools/loaders/__pycache__/NS.cpython-39.pyc
aerosoltools/loaders/__pycache__/OPCN3.cpython-312.pyc
aerosoltools-0.1.7.dist-info/licenses/LICENSE
aerosoltools-0.1.7.dist-info/METADATA
aerosoltools-0.1.7.dist-info/WHEEL
aerosoltools-0.1.7.dist-info/top_level.txt
aerosoltools-0.1.7.dist-info/RECORD
