Metadata-Version: 2.4
Name: aerosoltools
Version: 0.1.7
Summary: Tools for loading and analyzing aerosol instrument data
Author: NRCWE community
Project-URL: Documentation, https://nfa-nrcwe.github.io/aerosoltools/
Classifier: Programming Language :: Python :: 3.10
Classifier: Programming Language :: Python :: 3.11
Classifier: Programming Language :: Python :: 3.12
Requires-Python: >=3.10
License-File: LICENSE
Requires-Dist: pandas>=1.0
Requires-Dist: numpy>=1.20
Requires-Dist: matplotlib>=3.1.0
Requires-Dist: tabulate>=0.8.0
Requires-Dist: openpyxl
Provides-Extra: dev
Requires-Dist: pytest; extra == "dev"
Requires-Dist: ruff; extra == "dev"
Requires-Dist: black; extra == "dev"
Dynamic: license-file
